Mahi_STT/__init__.py
Mahi_STT-0.1.dist-info/METADATA
Mahi_STT-0.1.dist-info/WHEEL
Mahi_STT-0.1.dist-info/top_level.txt
Mahi_STT-0.1.dist-info/RECORD
